xslots.py
xslots-0.0.1.dist-info/METADATA
xslots-0.0.1.dist-info/WHEEL
xslots-0.0.1.dist-info/top_level.txt
xslots-0.0.1.dist-info/RECORD
