Metadata-Version: 2.1
Name: xslots
Version: 0.0.1
Summary: Generate Slot Counter
Home-page: UNKNOWN
Author: phoenixR
License: MIT
Platform: UNKNOWN
